colcon_ros_domain_id_coordinator/__init__.py
colcon_ros_domain_id_coordinator/shell/__init__.py
colcon_ros_domain_id_coordinator/shell/ros_domain_id.py
colcon_ros_domain_id_coordinator-0.2.4.dist-info/LICENSE
colcon_ros_domain_id_coordinator-0.2.4.dist-info/METADATA
colcon_ros_domain_id_coordinator-0.2.4.dist-info/WHEEL
colcon_ros_domain_id_coordinator-0.2.4.dist-info/entry_points.txt
colcon_ros_domain_id_coordinator-0.2.4.dist-info/top_level.txt
colcon_ros_domain_id_coordinator-0.2.4.dist-info/zip-safe
colcon_ros_domain_id_coordinator-0.2.4.dist-info/RECORD
